__init__.py
functions.py
ft_package_polar_42-0.0.2.dist-info/METADATA
ft_package_polar_42-0.0.2.dist-info/WHEEL
ft_package_polar_42-0.0.2.dist-info/licenses/LICENSE
ft_package_polar_42-0.0.2.dist-info/RECORD
